LICENSE
MANIFEST.in
README.md
setup.cfg
setup.py
django_parrot/__init__.py
django_parrot/apps.py
django_parrot/models.py
django_parrot/serializers.py
django_parrot/token_auth_provider.py
django_parrot/urls.py
django_parrot.egg-info/PKG-INFO
django_parrot.egg-info/SOURCES.txt
django_parrot.egg-info/dependency_links.txt
django_parrot.egg-info/requires.txt
django_parrot.egg-info/top_level.txt
django_parrot/migrations/0001_initial.py
django_parrot/migrations/__init__.py
django_parrot/receiver/__init__.py
django_parrot/receiver/views.py
django_parrot/sender/__init__.py
django_parrot/sender/recorder.py
django_parrot/sender/replayer.py
django_parrot/tests/__init__.py
django_parrot/tests/dummy_view.py
django_parrot/tests/test_settings.py
django_parrot/tests/test_urls.py
django_parrot/tests/receiver/__init__.py
django_parrot/tests/receiver/test_views.py
django_parrot/tests/sender/__init__.py
django_parrot/tests/sender/test_recorder.py
django_parrot/tests/sender/test_replayer.py